odoo/addons/l10n_fr_fec_oca/README.rst
odoo/addons/l10n_fr_fec_oca/__init__.py
odoo/addons/l10n_fr_fec_oca/__manifest__.py
odoo/addons/l10n_fr_fec_oca/i18n/fr.po
odoo/addons/l10n_fr_fec_oca/i18n/l10n_fr_fec.pot
odoo/addons/l10n_fr_fec_oca/i18n/l10n_fr_fec_oca.pot
odoo/addons/l10n_fr_fec_oca/readme/CONTRIBUTORS.rst
odoo/addons/l10n_fr_fec_oca/readme/DESCRIPTION.rst
odoo/addons/l10n_fr_fec_oca/readme/USAGE.rst
odoo/addons/l10n_fr_fec_oca/static/description/icon.png
odoo/addons/l10n_fr_fec_oca/static/description/index.html
odoo/addons/l10n_fr_fec_oca/wizard/__init__.py
odoo/addons/l10n_fr_fec_oca/wizard/account_fr_fec_oca.py
odoo/addons/l10n_fr_fec_oca/wizard/account_fr_fec_oca_view.xml
odoo12_addon_l10n_fr_fec_oca-12.0.1.1.0.dist-info/METADATA
odoo12_addon_l10n_fr_fec_oca-12.0.1.1.0.dist-info/WHEEL
odoo12_addon_l10n_fr_fec_oca-12.0.1.1.0.dist-info/top_level.txt
odoo12_addon_l10n_fr_fec_oca-12.0.1.1.0.dist-info/RECORD
