Metadata-Version: 2.1
Name: odoo12-addon-l10n-fr-fec-oca
Version: 12.0.1.1.0
Summary: Fichier d'Échange Informatisé (FEC) for France
Home-page: https://github.com/OCA/l10n-france
Author: Akretion,Odoo Community Association (OCA)
Author-email: support@odoo-community.org
License: LGPL-3
Platform: UNKNOWN
Classifier: Programming Language :: Python
Classifier: Framework :: Odoo
Classifier: Framework :: Odoo :: 12.0
Classifier: License :: OSI Approved :: GNU Lesser General Public License v3 (LGPLv3)
Requires-Python: >=3.5
Requires-Dist: odoo12-addon-date-range
Requires-Dist: odoo <12.1dev,>=12.0a
Requires-Dist: unicodecsv
Requires-Dist: unidecode
